<?xml version="1.0" encoding="utf-8" ?>
<odoo>
    <data>
        <record id="invoice_add_stock_location_id_form" model="ir.ui.view">
            <field name="name">invoice_add_stock_location_id_form</field>
            <field name="model">account.move</field>
            <field name="inherit_id" ref="account.view_move_form" />
            <field name="priority" eval="80" />
            <field name="arch" type="xml">
                <notebook position="inside">
                    <page string="Stock">
                        <group>
                            <field name="stock_move_id" />
                        </group>
                    </page>
                </notebook>
            </field>
        </record>
    </data>
</odoo>
