<?xml version="1.0" encoding="utf-8" ?>
<odoo>
    <record id="view_daily_stock_report_form" model="ir.ui.view">
        <field name="name">stock.daily.stock.report</field>
        <field name="model">stock.daily.stock.report</field>
        <field name="arch" type="xml">
            <form string="Report Options">
                <group name="filters">
                    <group>
                        <field name="location_id" />
                        <field name="mode" />
                    </group>
                    <group name="date_range">
                        <field
                            name="date_range_id"
                            domain="['|',('company_id','=',company_id), ('company_id','=',False)]"
                        />
                        <field name="date_from" />
                        <field name="date_to" />
                        <field name="company_id" invisible="1" />
                    </group>
                </group>
                <footer>
                    <button
                        name="button_show"
                        string="Show"
                        type="object"
                        default_focus="1"
                        class="oe_highlight"
                    />
                    or
                    <button name="button_print" string="Print" type="object" />
                    or
                    <button string="Cancel" class="oe_link" special="cancel" />
                </footer>
            </form>
        </field>
    </record>
    <record id="action_daily_stock_report" model="ir.actions.act_window">
        <field name="name">Daily Stock Report</field>
        <field name="res_model">stock.daily.stock.report</field>
        <field name="view_mode">form</field>
        <field name="target">new</field>
    </record>
    <menuitem
        id="menu_daily_stock_report"
        name="Daily Stock Report"
        action="action_daily_stock_report"
        parent="stock.menu_warehouse_report"
        groups="account.group_account_user"
    />
    <record id="action_stock_report" model="ir.actions.act_window">
        <field name="name">Stock Report</field>
        <field name="res_model">stock.daily.stock.report</field>
        <field name="view_mode">form</field>
        <field name="target">new</field>
        <field name="context">{'default_mode':'product'}</field>
    </record>
    <menuitem
        id="menu_stock_report"
        name="Stock Report"
        action="action_stock_report"
        parent="stock.menu_warehouse_report"
        groups="account.group_account_user"
    />
    <record id="action_daily_stock_report_line" model="ir.actions.act_window">
        <field name="name">Daily Stock Report</field>
        <field name="res_model">stock.daily.stock.report.line</field>
        <field name="view_mode">tree,form</field>
        <field name="domain">[('report_id','=',active_id)]</field>
    </record>
    <record id="view_daily_stock_report_line_tree" model="ir.ui.view">
        <field name="name">stock.daily.stock.report.line</field>
        <field name="model">stock.daily.stock.report.line</field>
        <field name="arch" type="xml">
            <tree edit="0" create="0" import="0">
                <!--                js_class="daily_stock_report_list">-->
                <field name="type" />
                <field name="product_id" />
                <field name="quantity" sum="1" />
                <field name="amount" sum="1" />
                <button
                    name="action_valuation_at_date_details"
                    aria-label="Valuation"
                    title="Valuation"
                    type="object"
                    icon="fa-info-circle"
                />
            </tree>
        </field>
    </record>
    <record id="view_daily_stock_report_line_form" model="ir.ui.view">
        <field name="name">stock.daily.stock.report.line</field>
        <field name="model">stock.daily.stock.report.line</field>
        <field name="arch" type="xml">
            <form>
                <sheet>
                    <group>
                        <group>
                            <field name="product_id" />
                            <field name="type" />
                        </group>
                        <group>
                            <field name="amount" />
                            <field name="quantity" />
                        </group>
                    </group>
                    <field name="valuation_ids" />
                </sheet>
            </form>
        </field>
    </record>
    <record id="action_daily_stock_report_ref" model="ir.actions.act_window">
        <field name="name">Daily Stock Report</field>
        <field name="res_model">stock.daily.stock.report.ref</field>
        <field name="view_mode">tree</field>
        <field name="domain">[('report_id','=',active_id)]</field>
    </record>
    <record id="view_daily_stock_report_ref_tree" model="ir.ui.view">
        <field name="name">stock.daily.stock.report.ref</field>
        <field name="model">stock.daily.stock.report.ref</field>
        <field name="arch" type="xml">
            <tree edit="0" create="0" import="0">
                <field name="type" />
                <field name="ref" />
                <field name="amount" sum="1" />
                <button
                    name="action_valuation_at_date_details"
                    aria-label="Valuation"
                    title="Valuation"
                    type="object"
                    icon="fa-info-circle"
                />
            </tree>
        </field>
    </record>
    <record id="view_daily_stock_report_ref_form" model="ir.ui.view">
        <field name="name">stock.daily.stock.report.ref</field>
        <field name="model">stock.daily.stock.report.ref</field>
        <field name="arch" type="xml">
            <form>
                <sheet>
                    <group>
                        <group>
                            <field name="ref" />
                            <field name="type" />
                        </group>
                        <group>
                            <field name="amount" />
                            <field name="quantity" />
                        </group>
                    </group>
                    <field name="valuation_ids" />
                </sheet>
            </form>
        </field>
    </record>
</odoo>
